my_package/__init__.py
my_package/moduel.py
jupsec-0.1.0.dist-info/METADATA
jupsec-0.1.0.dist-info/WHEEL
jupsec-0.1.0.dist-info/top_level.txt
jupsec-0.1.0.dist-info/RECORD
